docdict/DocString2Json.py
docdict/__init__.py
docdict-0.0.2.dist-info/LICENSE
docdict-0.0.2.dist-info/METADATA
docdict-0.0.2.dist-info/WHEEL
docdict-0.0.2.dist-info/top_level.txt
docdict-0.0.2.dist-info/RECORD
